orsm/__init__.py
orsm/_version.py
orsm/cli/__init__.py
orsm/cli/cli.py
orsm/cli/repo.py
orsm/cli/tests/__init__.py
orsm/cli/tests/cli_print_logs.py
orsm/cli/tests/test_repo.py
orsm/combinations/__init__.py
orsm/combinations/combinations.py
orsm/combinations/tests/__init__.py
orsm/combinations/tests/test_combinations.py
orsm/decorators/__init__.py
orsm/decorators/disabling.py
orsm/decorators/nullifying.py
orsm/decorators/tests/__init__.py
orsm/decorators/tests/test_decorators.py
orsm/logger/__init__.py
orsm/logger/logger.py
orsm/logger/demos/demo_logger.py
orsm/logger/tests/__init__.py
orsm/logger/tests/test_logger.py
orsm/outputs/__init__.py
orsm/outputs/suppressors.py
orsm/outputs/tests/__init__.py
orsm/outputs/tests/test_suppressors.py
orsm/profilers/__init__.py
orsm/profilers/_query_runtime_environment.py
orsm/profilers/demos/__init__.py
orsm/profilers/demos/profiling_decorated_function.py
orsm/profilers/memory/__init__.py
orsm/profilers/memory/memory_profilers.py
orsm/profilers/time/__init__.py
orsm/profilers/time/time_profilers.py
orsm/timing/__init__.py
orsm/timing/timing.py
orsm/timing/tests/__init__.py
orsm/timing/tests/test_timing.py
orsm/variables/__init__.py
orsm/variables/variables.py
orsm/variables/tests/__init__.py
orsm/variables/tests/test_variables.py
orsm/variables/tests/variables_foo.py
orsm-0.0.5.dist-info/LICENSE.md
orsm-0.0.5.dist-info/METADATA
orsm-0.0.5.dist-info/WHEEL
orsm-0.0.5.dist-info/top_level.txt
orsm-0.0.5.dist-info/RECORD
