Metadata-Version: 2.1
Name: orsm
Version: 0.0.5
Summary: Useful utility scripts
Author-email: Dr Oliver Sheridan-Methven <oliver.sheridan-methven@hotmail.co.uk>
Project-URL: Homepage, https://github.com/oliversheridanmethven/orsm
Project-URL: Issues, https://github.com/oliversheridanmethven/orsm/issues
Classifier: Programming Language :: Python :: 3
Classifier: License :: OSI Approved :: MIT License
Classifier: Operating System :: OS Independent
Requires-Python: >=3.12
License-File: LICENSE.md
Requires-Dist: binding
Requires-Dist: haggis
Requires-Dist: line-profiler
Requires-Dist: py
Requires-Dist: termcolor
Requires-Dist: testfixtures
Requires-Dist: tqdm
Requires-Dist: varname >=0.13.3
Requires-Dist: executing
Requires-Dist: asttokens
Provides-Extra: dev
Requires-Dist: mkdocs ; extra == 'dev'
Requires-Dist: mkdocs-material ; extra == 'dev'
Requires-Dist: mkdocs-exclude ; extra == 'dev'
Requires-Dist: mkdocs-same-dir ; extra == 'dev'
Requires-Dist: mkdocs-awesome-pages-plugin ; extra == 'dev'
Requires-Dist: mkdocs-git-revision-date-localized-plugin ; extra == 'dev'
Requires-Dist: mkdocs-material[imaging] ; extra == 'dev'
Requires-Dist: mkdocstrings ; extra == 'dev'
Requires-Dist: mkdocstrings-python ; extra == 'dev'
Requires-Dist: mkdocs-literate-nav ; extra == 'dev'
Requires-Dist: mkdocs-section-index ; extra == 'dev'
Requires-Dist: mkdocs-gen-files ; extra == 'dev'
Requires-Dist: mike ; extra == 'dev'
